<zombieServer>
	<map name="Mall of the Dead"></map>
	<map author="Lorenc"></map>
	<map helicopter="1479.2422, -1639.6296, 15.2488"></map>
	
	<map human_spawn="1511.9077, -1674.1685, 14.5909"></map>
	<map human_spawn="1530.6058, -1619.4143, 14.1556"></map>
	<map human_spawn="1511.2009, -1621.9099, 15.2556"></map>
	
	<map zombie_spawn="1447.7231, -1620.8060, 15.2556"></map>
	<map zombie_spawn="1442.4087, -1668.1334, 13.8876"></map>
	<map zombie_spawn="1444.4915, -1693.5100, 15.8433"></map>

	<object model="3934" posX="1479.3400000" posY="-1639.6500000" posZ="13.6500000" rotX="0.0000000" rotY="0.0000000" rotZ="0.0000000"/>
	<object model="1219" posX="1555.7700000" posY="-1675.6600000" posZ="16.6800000" rotX="0.0000000" rotY="90.0000000" rotZ="0.0000000"/>
	<object model="1219" posX="1498.6000000" posY="-1580.0500000" posZ="16.6800000" rotX="0.0000000" rotY="90.0000000" rotZ="-90.0000000"/>
	<object model="1219" posX="1498.6000000" posY="-1580.0500000" posZ="14.2200000" rotX="0.0000000" rotY="90.0000000" rotZ="-90.0000000"/>
	<object model="8149" posX="1534.6700000" posY="-1640.9200000" posZ="15.3800000" rotX="0.0000000" rotY="0.0000000" rotZ="180.0000000"/>
	<object model="8149" posX="1534.6700000" posY="-1791.2900000" posZ="15.3800000" rotX="0.0000000" rotY="0.0000000" rotZ="180.0000000"/>
	<object model="4230" posX="1534.3300000" posY="-1701.5100000" posZ="-47.9500000" rotX="0.6600000" rotY="90.0000000" rotZ="-0.1200000"/>
	<object model="3594" posX="1528.5300000" posY="-1621.8000000" posZ="12.8200000" rotX="0.0000000" rotY="0.0000000" rotZ="66.7200000"/>
	<object model="3594" posX="1527.2000000" posY="-1595.1300000" posZ="12.8100000" rotX="0.0000000" rotY="0.0000000" rotZ="66.7200000"/>
	<object model="3594" posX="1490.0200000" posY="-1619.5100000" posZ="13.4600000" rotX="0.0000000" rotY="0.0000000" rotZ="66.7200000"/>
	<object model="3594" posX="1495.1700000" posY="-1652.4700000" posZ="13.4600000" rotX="0.0000000" rotY="0.0000000" rotZ="-53.1000000"/>
	<object model="3594" posX="1464.9000000" posY="-1655.5000000" posZ="13.4600000" rotX="0.0000000" rotY="0.0000000" rotZ="-53.1000000"/>
	<object model="3594" posX="1478.4300000" posY="-1684.9700000" posZ="13.4600000" rotX="0.0000000" rotY="0.0000000" rotZ="59.5200000"/>
	<object model="3594" posX="1500.0200000" posY="-1675.5100000" posZ="13.4600000" rotX="0.0000000" rotY="0.0000000" rotZ="116.3400000"/>
	<object model="3594" posX="1455.1200000" posY="-1674.1600000" posZ="13.4600000" rotX="0.0000000" rotY="0.0000000" rotZ="238.5600000"/>
	<object model="3594" posX="1447.8900000" posY="-1690.8400000" posZ="13.4600000" rotX="0.0000000" rotY="0.0000000" rotZ="238.5600000"/>
	<object model="3594" posX="1456.7800000" posY="-1719.8100000" posZ="13.4600000" rotX="-7.8000000" rotY="-12.6000000" rotZ="137.6400000"/>
	<object model="3594" posX="1501.3300000" posY="-1717.2200000" posZ="13.4600000" rotX="0.0000000" rotY="0.0000000" rotZ="273.4800000"/>
	<object model="3594" posX="1513.9200000" posY="-1658.5900000" posZ="12.8200000" rotX="0.0000000" rotY="0.0000000" rotZ="66.7200000"/>
	<object model="3594" posX="1525.5400000" posY="-1728.9400000" posZ="12.8200000" rotX="0.0000000" rotY="0.0000000" rotZ="-52.4400000"/>
	<object model="8149" posX="1534.6700000" posY="-1791.2900000" posZ="22.5000000" rotX="0.0000000" rotY="0.0000000" rotZ="180.0000000"/>
	<object model="8149" posX="1534.6700000" posY="-1640.9200000" posZ="22.5000000" rotX="0.0000000" rotY="0.0000000" rotZ="180.0000000"/>
	<object model="8149" posX="1464.7200000" posY="-1741.1100000" posZ="15.3800000" rotX="0.0000000" rotY="0.0000000" rotZ="90.0000000"/>
	<object model="8149" posX="1464.7200000" posY="-1741.1100000" posZ="22.5000000" rotX="0.0000000" rotY="0.0000000" rotZ="90.0000000"/>
	<object model="8149" posX="1421.7200000" posY="-1669.4400000" posZ="15.3800000" rotX="0.0000000" rotY="0.0000000" rotZ="0.0000000"/>
	<object model="8149" posX="1421.7200000" posY="-1669.4400000" posZ="22.5000000" rotX="0.0000000" rotY="0.0000000" rotZ="0.0000000"/>
	<object model="8149" posX="1493.5200000" posY="-1590.3600000" posZ="15.3800000" rotX="0.0000000" rotY="0.0000000" rotZ="-90.0000000"/>
	<object model="8149" posX="1493.5200000" posY="-1590.3600000" posZ="22.5000000" rotX="0.0000000" rotY="0.0000000" rotZ="-90.0000000"/>
	<object model="849" posX="1492.1800000" posY="-1627.5700000" posZ="13.3100000" rotX="0.0000000" rotY="0.0000000" rotZ="0.0000000"/>
	<object model="849" posX="1505.2700000" posY="-1635.3000000" posZ="13.3100000" rotX="0.0000000" rotY="0.0000000" rotZ="0.0000000"/>
	<object model="849" posX="1461.7700000" posY="-1651.3400000" posZ="13.3100000" rotX="0.0000000" rotY="0.0000000" rotZ="130.3800000"/>
	<object model="849" posX="1487.9200000" posY="-1656.0000000" posZ="13.3100000" rotX="0.0000000" rotY="0.0000000" rotZ="-69.9000000"/>
	<object model="849" posX="1460.3700000" posY="-1675.7900000" posZ="13.3100000" rotX="0.0000000" rotY="0.0000000" rotZ="40.5600000"/>
	<object model="849" posX="1446.1500000" posY="-1686.7200000" posZ="13.3100000" rotX="0.0000000" rotY="0.0000000" rotZ="40.5600000"/>
	<object model="849" posX="1475.0300000" posY="-1686.2400000" posZ="13.3100000" rotX="0.0000000" rotY="0.0000000" rotZ="40.5600000"/>
	<object model="849" posX="1499.3200000" posY="-1673.2200000" posZ="13.3100000" rotX="0.0000000" rotY="0.0000000" rotZ="40.5600000"/>
	<object model="849" posX="1498.6800000" posY="-1644.1500000" posZ="13.3100000" rotX="0.0000000" rotY="0.0000000" rotZ="151.8600000"/>
	<object model="1441" posX="1480.6300000" posY="-1620.3300000" posZ="13.6800000" rotX="0.0000000" rotY="0.0000000" rotZ="0.0000000"/>
	<object model="1441" posX="1471.8500000" posY="-1613.6400000" posZ="13.6800000" rotX="0.0000000" rotY="0.0000000" rotZ="-107.8200000"/>
	<object model="1441" posX="1462.4800000" posY="-1634.5300000" posZ="13.6800000" rotX="0.0000000" rotY="0.0000000" rotZ="-107.8200000"/>
	<object model="1441" posX="1474.8300000" posY="-1658.3500000" posZ="13.6800000" rotX="0.0000000" rotY="0.0000000" rotZ="-182.9400000"/>
	<object model="1441" posX="1474.9400000" posY="-1691.6500000" posZ="13.6800000" rotX="0.0000000" rotY="0.0000000" rotZ="-182.9400000"/>
	<object model="1441" posX="1473.6400000" posY="-1712.2000000" posZ="13.6800000" rotX="0.0000000" rotY="0.0000000" rotZ="-72.6000000"/>
	<object model="1441" posX="1455.1100000" posY="-1717.5400000" posZ="13.6800000" rotX="0.0000000" rotY="0.0000000" rotZ="-152.2800000"/>
	<object model="1441" posX="1449.7300000" posY="-1695.3900000" posZ="13.6800000" rotX="0.0000000" rotY="0.0000000" rotZ="-219.9000000"/>
	<object model="3594" posX="1444.7900000" posY="-1667.3400000" posZ="12.9400000" rotX="0.0000000" rotY="0.0000000" rotZ="238.5600000"/>
	<object model="1441" posX="1442.7100000" posY="-1671.2800000" posZ="13.1900000" rotX="0.0000000" rotY="0.0000000" rotZ="-219.9000000"/>
	<object model="1219" posX="1527.0500000" posY="-1616.1600000" posZ="12.5800000" rotX="0.0000000" rotY="0.0000000" rotZ="0.0000000"/>
	<object model="1219" posX="1530.7200000" posY="-1600.1500000" posZ="12.5800000" rotX="0.0000000" rotY="0.0000000" rotZ="-75.4200000"/>
	<object model="1219" posX="1516.6900000" posY="-1655.4000000" posZ="12.5800000" rotX="0.0000000" rotY="0.0000000" rotZ="-75.4200000"/>
	<object model="1219" posX="1527.6100000" posY="-1681.6400000" posZ="12.5800000" rotX="0.0000000" rotY="0.0000000" rotZ="-75.4200000"/>
	<object model="1219" posX="1526.4500000" posY="-1723.7100000" posZ="12.5800000" rotX="0.0000000" rotY="0.0000000" rotZ="-75.4200000"/>
	<object model="1219" posX="1495.6400000" posY="-1724.1300000" posZ="12.5800000" rotX="0.0000000" rotY="0.0000000" rotZ="-75.4200000"/>
	<object model="1219" posX="1459.0800000" posY="-1723.7700000" posZ="12.5800000" rotX="0.0000000" rotY="0.0000000" rotZ="-75.4200000"/>
	<object model="619" posX="1461.0800000" posY="-1707.4700000" posZ="12.3600000" rotX="0.0000000" rotY="0.0000000" rotZ="0.0000000"/>
	<object model="619" posX="1460.1500000" posY="-1687.7700000" posZ="12.3600000" rotX="0.0000000" rotY="0.0000000" rotZ="-174.8400000"/>
	<object model="619" posX="1496.0100000" posY="-1687.1700000" posZ="12.3600000" rotX="0.0000000" rotY="0.0000000" rotZ="-113.5200000"/>
	<object model="619" posX="1502.7500000" posY="-1621.3000000" posZ="12.3600000" rotX="0.0000000" rotY="0.0000000" rotZ="-145.9800000"/>
	<object model="818" posX="1480.9900000" posY="-1620.7700000" posZ="15.5000000" rotX="0.0000000" rotY="0.0000000" rotZ="-36.7200000"/>
	<object model="818" posX="1492.5600000" posY="-1627.7600000" posZ="15.5000000" rotX="0.0000000" rotY="0.0000000" rotZ="0.0000000"/>
	<object model="818" posX="1496.0400000" posY="-1648.6200000" posZ="15.5000000" rotX="0.0000000" rotY="0.0000000" rotZ="65.2200000"/>
	<object model="818" posX="1464.0200000" posY="-1653.3000000" posZ="15.5000000" rotX="0.0000000" rotY="0.0000000" rotZ="40.4400000"/>
	<object model="818" posX="1469.5100000" posY="-1663.2200000" posZ="15.5000000" rotX="0.0000000" rotY="0.0000000" rotZ="0.0000000"/>
	<object model="818" posX="1454.7900000" posY="-1678.5500000" posZ="15.5000000" rotX="0.0000000" rotY="0.0000000" rotZ="25.5000000"/>
	<object model="818" posX="1447.1500000" posY="-1693.5400000" posZ="15.5000000" rotX="0.0000000" rotY="0.0000000" rotZ="23.4000000"/>
	<object model="818" posX="1473.0500000" posY="-1710.0500000" posZ="15.5000000" rotX="0.0000000" rotY="0.0000000" rotZ="0.0000000"/>
	<object model="818" posX="1476.8200000" posY="-1687.5600000" posZ="15.5000000" rotX="0.0000000" rotY="0.0000000" rotZ="0.0000000"/>
	<object model="818" posX="1497.0200000" posY="-1674.0900000" posZ="15.5000000" rotX="0.0000000" rotY="0.0000000" rotZ="0.0000000"/>
	<object model="818" posX="1443.4000000" posY="-1670.0300000" posZ="15.5000000" rotX="0.0000000" rotY="0.0000000" rotZ="37.8000000"/>
	<object model="818" posX="1513.3200000" posY="-1658.1800000" posZ="15.5000000" rotX="0.0000000" rotY="0.0000000" rotZ="-116.2800000"/>
	<object model="818" posX="1526.6900000" posY="-1617.5400000" posZ="15.5000000" rotX="0.0000000" rotY="0.0000000" rotZ="-49.2000000"/>
	<object model="818" posX="1529.0700000" posY="-1599.3600000" posZ="15.5000000" rotX="0.0000000" rotY="0.0000000" rotZ="0.0000000"/>
	<object model="3594" posX="1431.6700000" posY="-1599.0500000" posZ="12.7000000" rotX="0.0000000" rotY="0.0000000" rotZ="66.7200000"/>
	<object model="818" posX="1433.7600000" posY="-1598.5000000" posZ="15.5000000" rotX="0.0000000" rotY="0.0000000" rotZ="-49.2000000"/>
	<object model="3594" posX="1431.4500000" posY="-1727.8600000" posZ="12.8000000" rotX="0.0000000" rotY="0.0000000" rotZ="238.5600000"/>
	<object model="818" posX="1431.3300000" posY="-1724.9800000" posZ="15.5000000" rotX="0.0000000" rotY="0.0000000" rotZ="23.4000000"/>
	<object model="818" posX="1498.1000000" posY="-1721.0000000" posZ="15.5000000" rotX="0.0000000" rotY="0.0000000" rotZ="0.0000000"/>
	<object model="818" posX="1525.9100000" posY="-1726.2300000" posZ="15.5000000" rotX="0.0000000" rotY="0.0000000" rotZ="0.0000000"/>
	<object model="818" posX="1458.4400000" posY="-1720.8800000" posZ="15.5000000" rotX="0.0000000" rotY="0.0000000" rotZ="0.0000000"/>
	<object model="818" posX="1458.9200000" posY="-1687.8300000" posZ="15.5000000" rotX="0.0000000" rotY="0.0000000" rotZ="0.0000000"/>
	<object model="818" posX="1461.2800000" posY="-1705.9000000" posZ="15.5000000" rotX="0.0000000" rotY="0.0000000" rotZ="0.0000000"/>
	<object model="818" posX="1459.7800000" posY="-1623.4600000" posZ="15.5000000" rotX="0.0000000" rotY="0.0000000" rotZ="-36.7800000"/>
	<object model="818" posX="1458.9200000" posY="-1687.8300000" posZ="15.5000000" rotX="0.0000000" rotY="0.0000000" rotZ="0.0000000"/>
	<object model="818" posX="1457.2900000" posY="-1618.2000000" posZ="15.5000000" rotX="0.0000000" rotY="0.0000000" rotZ="-36.7800000"/>
	<object model="818" posX="1478.8200000" posY="-1665.3900000" posZ="15.5000000" rotX="0.0000000" rotY="0.0000000" rotZ="-45.9600000"/>
	<object model="818" posX="1488.8900000" posY="-1665.6400000" posZ="15.5000000" rotX="0.0000000" rotY="0.0000000" rotZ="42.1200000"/>
	<object model="818" posX="1493.4400000" posY="-1692.1400000" posZ="15.5000000" rotX="0.0000000" rotY="0.0000000" rotZ="56.4600000"/>
	<object model="818" posX="1497.5100000" posY="-1684.9000000" posZ="15.5000000" rotX="0.0000000" rotY="0.0000000" rotZ="-24.4800000"/>
	<object model="818" posX="1495.1000000" posY="-1703.4700000" posZ="15.5000000" rotX="0.0000000" rotY="0.0000000" rotZ="26.4000000"/>
	<object model="818" posX="1501.8100000" posY="-1622.1100000" posZ="15.5000000" rotX="0.0000000" rotY="0.0000000" rotZ="0.0000000"/>
	<object model="818" posX="1499.8100000" posY="-1617.4100000" posZ="15.5000000" rotX="0.0000000" rotY="0.0000000" rotZ="64.9800000"/>
	<object model="818" posX="1499.7800000" posY="-1617.3500000" posZ="15.5000000" rotX="0.0000000" rotY="0.0000000" rotZ="64.9800000"/>
	<object model="3594" posX="1447.9300000" posY="-1696.0400000" posZ="13.4600000" rotX="-8.4000000" rotY="-0.9000000" rotZ="174.3600000"/>
	<object model="3594" posX="1448.6300000" posY="-1691.1600000" posZ="13.9500000" rotX="16.0800000" rotY="-2.7000000" rotZ="176.3400000"/>
	<object model="1231" posX="1464.8200000" posY="-1637.0400000" posZ="13.1600000" rotX="270.0000000" rotY="14.9400000" rotZ="0.1400000"/>
	<object model="1231" posX="1467.0400000" posY="-1626.5500000" posZ="13.1600000" rotX="270.0000000" rotY="14.9400000" rotZ="-79.0600000"/>
	<object model="1231" posX="1476.0700000" posY="-1655.1000000" posZ="13.1600000" rotX="270.0000000" rotY="14.9400000" rotZ="-79.0600000"/>
</zombieServer>